{
  "manifest": {
    "apis": {
      "custom": {
        "endpoint": {
          "uri": "arn:aws:lambda:us-east-1:737504307327:function:84916d3b-4150-496f-afa8-daff858852a8:Release_0"
        }
      }
    },
    "manifestVersion": "1.0",
    "publishingInformation": {
      "category": "KNOWLEDGE_AND_TRIVIA",
      "distributionCountries": [],
      "isAvailableWorldwide": true,
      "locales": {
        "ja-JP": {
          "description": "Sample Full Description",
          "examplePhrases": [
            "Alexa open hello world",
            "hello",
            "help"
          ],
          "keywords": [],
          "name": "ハローワールド",
          "summary": "Sample Short Description"
        }
      },
      "testingInstructions": "Sample Testing Instructions."
    }
  }
}